README.md
setup.py
move_as_human/__init__.py
move_as_human/example_usage.py
move_as_human/human_mouse_movement.py
move_as_human/install.py
move_as_human/linkedin_browser.py
move_as_human/main.py
move_as_human/mouse_trajectory_visualizer.py
move_as_human.egg-info/PKG-INFO
move_as_human.egg-info/SOURCES.txt
move_as_human.egg-info/dependency_links.txt
move_as_human.egg-info/requires.txt
move_as_human.egg-info/top_level.txt
pyarmor_runtime_000000/__init__.py
pyarmor_runtime_000000/pyarmor_runtime.pyd