Metadata-Version: 2.4
Name: move_as_human
Version: 0.6.8
Summary: a move as human library , support both win and mac 
Author: dkflex
Author-email: 
Keywords: python,move as human,move_as_human,windows
Classifier: Development Status :: 1 - Planning
Classifier: Intended Audience :: Developers
Classifier: Programming Language :: Python :: 3
Classifier: Operating System :: Microsoft :: Windows
Requires-Dist: pyautogui
Requires-Dist: numpy
Dynamic: author
Dynamic: classifier
Dynamic: description
Dynamic: description-content-type
Dynamic: keywords
Dynamic: requires-dist
Dynamic: summary
